fd
fd.py
setup.py
fd.egg-info/PKG-INFO
fd.egg-info/SOURCES.txt
fd.egg-info/dependency_links.txt
fd.egg-info/requires.txt
fd.egg-info/top_level.txt