Metadata-Version: 1.0
Name: fd
Version: 0.6
Summary: File system database (fd)
Home-page: UNKNOWN
Author: John Emmons
Author-email: emmons.john@gmail.com
License: UNKNOWN
Platform: UNKNOWN
